qcloudapi3/__init__.py
qcloudapi3/__version__.py
qcloudapi3/params.py
qcloudapi3/qcloudapi.py
qcloudapi3/common/__init__.py
qcloudapi3/common/request.py
qcloudapi3/common/sign.py
qcloudapi3/modules/__init__.py
qcloudapi3/modules/account.py
qcloudapi3/modules/base.py
qcloudapi3/modules/bill.py
qcloudapi3/modules/cmq.py
qcloudapi3/modules/cvm.py
qcloudapi3/modules/scf.py
qcloudapi3/modules/tmt.py
qcloudapi3/modules/wenzhi.py
qcloudapi3-0.3.0.dist-info/DESCRIPTION.rst
qcloudapi3-0.3.0.dist-info/METADATA
qcloudapi3-0.3.0.dist-info/RECORD
qcloudapi3-0.3.0.dist-info/WHEEL
qcloudapi3-0.3.0.dist-info/metadata.json
qcloudapi3-0.3.0.dist-info/top_level.txt
