Metadata-Version: 2.0
Name: qcloudapi3
Version: 0.3.0
Summary: qcloudapi3是为了让Python3开发者能够在自己的代码里更快捷方便的使用腾讯云的API而开发的SDK工具包。
Home-page: https://github.com/duyixian1234/api-python-sdk
Author: Yixian Du
Author-email: duyixian1234@outlook.com
License: MIT
Platform: UNKNOWN
Classifier: License :: OSI Approved :: MIT License
Classifier: Programming Language :: Python
Classifier: Programming Language :: Python :: 2.6
Classifier: Programming Language :: Python :: 2.7
Classifier: Programming Language :: Python :: 3
Classifier: Programming Language :: Python :: 3.3
Classifier: Programming Language :: Python :: 3.4
Classifier: Programming Language :: Python :: 3.5
Classifier: Programming Language :: Python :: 3.6
Classifier: Programming Language :: Python :: Implementation :: CPython
Classifier: Programming Language :: Python :: Implementation :: PyPy
Requires-Dist: requests
